MANIFEST.in
README.rst
setup.py
django_quick_photos.egg-info/PKG-INFO
django_quick_photos.egg-info/SOURCES.txt
django_quick_photos.egg-info/dependency_links.txt
django_quick_photos.egg-info/requires.txt
django_quick_photos.egg-info/top_level.txt
quickphotos/__init__.py
quickphotos/admin.py
quickphotos/apps.py
quickphotos/models.py
quickphotos/tests.py
quickphotos/utils.py
quickphotos/views.py
quickphotos/management/__init__.py
quickphotos/management/commands/__init__.py
quickphotos/management/commands/instagram_auth.py
quickphotos/management/commands/instagram_likes.py
quickphotos/management/commands/instagram_update.py
quickphotos/migrations/0001_initial.py
quickphotos/migrations/0002_thumb_to_standard_image.py
quickphotos/migrations/0003_counts.py
quickphotos/migrations/0004_photo_image_file.py
quickphotos/migrations/0005_tags.py
quickphotos/migrations/0006_likes.py
quickphotos/migrations/__init__.py
quickphotos/templatetags/__init__.py
quickphotos/templatetags/quickphotos_tags.py